hello.py
trituenhantaoio-0.0.1.dist-info/METADATA
trituenhantaoio-0.0.1.dist-info/WHEEL
trituenhantaoio-0.0.1.dist-info/top_level.txt
trituenhantaoio-0.0.1.dist-info/RECORD
