Metadata-Version: 2.1
Name: trituenhantaoio
Version: 0.0.1
Summary: Resource provided by trituenhantao.io.
Home-page: UNKNOWN
License: UNKNOWN
Platform: UNKNOWN
